{
  "$schema": "https://github.com/jopemachine/arvis-core/blob/master/workflow-schema.json",
  "creator": "Renan Cakirerk",
  "description": "A workflow that allows you to fuzzy search all open tabs, jump to any tab, close duplicate tabs, close tabs by keyword or url",
  "name": "Chrome Control",
  "readme": "A workflow that allows you to fuzzy search all open tabs, jump to any tab, close duplicate tabs, close tabs by keyword or url.\n\nAlfred Chrome Control Commands:\n\n`tabs`: Lists all tabs\n\n`close url <keywords>`: Close tabs with URLs matching these keywords\n\n`close title <keywords>`: Close tabs with titles matching these keywords\n\n`dedup`: Close duplicate tabs\n\nYou can find the source code of this workflow here [1]\n\nAlso see my \"How I Navigate Hundreds of Tabs on Chrome with JXA and Alfred\" article [2] if you're interested in learning how I created the workflow.\n\n[1] https://github.com/bit2pixel/chrome-control\n\n[2] https://medium.com/@bit2pixel/how-i-navigate-hundreds-of-tabs-on-chrome-with-jxa-and-alfred-9bbf971af02b",
  "version": "1.1.0",
  "defaultIcon": "icon.png",
  "webAddress": "https://medium.com/@bit2pixel/how-i-navigate-hundreds-of-tabs-on-chrome-with-jxa-and-alfred-9bbf971af02b",
  "enabled": true,
  "commands": [
    {
      "type": "keyword",
      "command": "close url",
      "title": "Close tab by URL",
      "subtitle": "",
      "withspace": true,
      "argType": "required",
      "actions": [
        {
          "modifiers": "normal",
          "type": "script",
          "script": "./chrome.js close --url $@ --ui"
        }
      ]
    },
    {
      "type": "keyword",
      "command": "close title",
      "title": "Close tab by title",
      "subtitle": "",
      "withspace": true,
      "argType": "required",
      "actions": [
        {
          "modifiers": "normal",
          "type": "script",
          "script": "./chrome.js close --title $@ --ui"
        }
      ]
    },
    {
      "type": "keyword",
      "command": "dedup",
      "title": "Dedup tabs",
      "subtitle": "",
      "withspace": false,
      "argType": "no",
      "actions": [
        {
          "modifiers": "normal",
          "type": "script",
          "script": "./chrome.js dedup --ui"
        }
      ]
    },
    {
      "type": "scriptFilter",
      "command": "tabs",
      "title": "List All Tabs",
      "subtitle": "Press enter to focus, hold alt to close the tab",
      "scriptFilter": "./chrome.js list",
      "runningSubtext": "Loading tabs...",
      "withspace": true,
      "argType": "optional",
      "actions": [
        {
          "modifiers": "normal",
          "type": "script",
          "script": "./chrome.js focus {query}"
        },
        {
          "modifiers": "opt",
          "type": "script",
          "script": "./chrome.js close {query} --ui --yes"
        }
      ]
    }
  ]
}
